cpdb_api/__init__.py
cpdb_api/request.py
cpdb_api-1.0.8.dist-info/LICENSE
cpdb_api-1.0.8.dist-info/METADATA
cpdb_api-1.0.8.dist-info/WHEEL
cpdb_api-1.0.8.dist-info/top_level.txt
cpdb_api-1.0.8.dist-info/RECORD
