Metadata-Version: 2.1
Name: cpdb-api
Version: 1.0.8
Summary: An API to access the NewClimate Institute's Climate Policy Database
Author-email: NewClimate Institute <info@newclimate.org>
Project-URL: Homepage, https://climatepolicydatabase.org
Project-URL: Source Code, https://github.com/KevinDackow/CPDB-API
Keywords: nci,cpdb,climatepolicydatabase,newclimateinstitute
Classifier: Programming Language :: Python :: 3
Classifier: License :: OSI Approved :: Apache Software License
Classifier: Operating System :: OS Independent
Requires-Python: >=3.7
License-File: LICENSE
Requires-Dist: pandas
Requires-Dist: requests
